AsympDirsCalculator/AsympDirsTools.py
AsympDirsCalculator/MAGCOSmacroFileGenerator.py
AsympDirsCalculator/MAGNETOCOSMICSimportingTools.py
AsympDirsCalculator/MAGNETOCOSMICSrun.py
AsympDirsCalculator/MAGNETOCOSMICSrunManager.py
AsympDirsCalculator/__init__.py
AsympDirsCalculator/globals.py
AsympDirsCalculator/magcos_running_scripts/AsymptoticDirection.g4mac
AsympDirsCalculator/magcos_running_scripts/runNoRewriteMAGCOSsimulation.sh
asympdirscalculator-1.0.14.dist-info/licenses/LICENSE
tests/__init__.py
tests/test_basic.py
asympdirscalculator-1.0.14.dist-info/METADATA
asympdirscalculator-1.0.14.dist-info/WHEEL
asympdirscalculator-1.0.14.dist-info/top_level.txt
asympdirscalculator-1.0.14.dist-info/RECORD
