Metadata-Version: 2.4
Name: AsympDirsCalculator
Version: 1.0.14
Summary: Python library containing tools for calculating asymptotic directions and vertical cut-off rigidities.
Home-page: https://github.com/ssc-maire/AsymptoticDirectionsCalculator-public
Author: Space Environment and Protection Group, University of Surrey
License: CC BY_NC_SA 4.0
Keywords: space physics earth asymptotic trajectory geomagnetic rigidity magnetocosmics
License-File: LICENSE
Requires-Dist: numpy>=1.21.6
Requires-Dist: pandas>=1.3.5
Requires-Dist: setuptools>=66.1.0
Requires-Dist: tqdm>=4.30.0
Requires-Dist: joblib>=1.2.0
Requires-Dist: wheel>=0.38.4
Requires-Dist: importlib-resources>=1.3.0; python_version < "3.9"
Dynamic: author
Dynamic: description
Dynamic: description-content-type
Dynamic: home-page
Dynamic: keywords
Dynamic: license
Dynamic: license-file
Dynamic: requires-dist
Dynamic: summary
